README.rst
pydto.py
setup.cfg
setup.py
pydto.egg-info/PKG-INFO
pydto.egg-info/SOURCES.txt
pydto.egg-info/dependency_links.txt
pydto.egg-info/top_level.txt