Metadata-Version: 1.1
Name: pydto
Version: 0.4.0
Summary: data validation and conversion library
Home-page: https://github.com/deemson/pydto
Author: Dmitry Kurkin
Author-email: dkurkin@toidev.com
License: MIT
Download-URL: https://pypi.python.org/pypi/pydto
Platform: any
Classifier: Development Status :: 4 - Beta
Classifier: Intended Audience :: Developers
Classifier: License :: OSI Approved :: MIT License
Classifier: Operating System :: OS Independent
Classifier: Programming Language :: Python :: 2
Classifier: Programming Language :: Python :: 2.6
Classifier: Programming Language :: Python :: 2.7
Classifier: Programming Language :: Python :: 3
Classifier: Programming Language :: Python :: 3.1
Classifier: Programming Language :: Python :: 3.2
Classifier: Programming Language :: Python :: 3.3
Classifier: Programming Language :: Python :: 3.4
